agg_python_bindings-0.1.4.dist-info/METADATA
agg_python_bindings-0.1.4.dist-info/WHEEL
agg_python_bindings-0.1.4.dist-info/licenses/LICENSE
agg_python_bindings/__init__.py
agg_python_bindings/__init__.pyi
agg_python_bindings/agg_python_bindings.cpython-310-x86_64-linux-gnu.so
agg_python_bindings/py.typed
agg_python_bindings-0.1.4.dist-info/RECORD
