Metadata-Version: 2.4
Name: agg_python_bindings
Version: 0.1.4
Classifier: Programming Language :: Rust
Classifier: Programming Language :: Python :: Implementation :: CPython
Classifier: Programming Language :: Python :: Implementation :: PyPy
License-File: LICENSE
Summary: Python bindings for the Rust graph library 'agg'
Requires-Python: >=3.8
